.dockerignore
.editorconfig
AUTHORS
CHANGELOG
CONTRIBUTING.rst
INSTALL.rst
LICENSE
MANIFEST.in
README.rst
babel.ini
pytest.ini
requirements-devel.txt
requirements.txt
run-tests.sh
setup.cfg
setup.py
.tx/config
docs/Makefile
docs/api.rst
docs/authors.rst
docs/changes.rst
docs/conf.py
docs/contributing.rst
docs/index.rst
docs/installation.rst
docs/license.rst
docs/make.bat
docs/usage.rst
examples/app.py
invenio_workflows_ui/__init__.py
invenio_workflows_ui/api.py
invenio_workflows_ui/cli.py
invenio_workflows_ui/config.py
invenio_workflows_ui/errors.py
invenio_workflows_ui/ext.py
invenio_workflows_ui/indexer.py
invenio_workflows_ui/permissions.py
invenio_workflows_ui/proxies.py
invenio_workflows_ui/receivers.py
invenio_workflows_ui/search.py
invenio_workflows_ui/tasks.py
invenio_workflows_ui/utils.py
invenio_workflows_ui.egg-info/PKG-INFO
invenio_workflows_ui.egg-info/SOURCES.txt
invenio_workflows_ui.egg-info/dependency_links.txt
invenio_workflows_ui.egg-info/entry_points.txt
invenio_workflows_ui.egg-info/not-zip-safe
invenio_workflows_ui.egg-info/requires.txt
invenio_workflows_ui.egg-info/top_level.txt
invenio_workflows_ui/mappings/__init__.py
invenio_workflows_ui/mappings/v5/__init__.py
invenio_workflows_ui/mappings/v5/workflows/record.json
invenio_workflows_ui/mappings/workflows/record.json
invenio_workflows_ui/serializers/__init__.py
invenio_workflows_ui/serializers/json.py
invenio_workflows_ui/serializers/response.py
invenio_workflows_ui/static/templates/invenio_workflows_ui/results.html
invenio_workflows_ui/templates/invenio_workflows_ui/base.html
invenio_workflows_ui/templates/invenio_workflows_ui/details.html
invenio_workflows_ui/templates/invenio_workflows_ui/index.html
invenio_workflows_ui/templates/invenio_workflows_ui/list.html
invenio_workflows_ui/templates/invenio_workflows_ui/utils.html
invenio_workflows_ui/views/__init__.py
invenio_workflows_ui/views/rest.py
invenio_workflows_ui/views/ui.py
tests/conftest.py
tests/test_invenio_workflows_serializer_response.py
tests/test_invenio_workflows_ui.py