Metadata-Version: 2.1
Name: invenio-workflows-ui
Version: 2.0.19
Summary: Invenio module which acts as a UI layer for invenio-workflows.
Home-page: https://github.com/inveniosoftware-contrib/invenio-workflows-ui
Author: CERN
Author-email: info@invenio-software.org
License: GPLv2
Keywords: invenio workflows gui interface content curation
Platform: any
Classifier: Environment :: Web Environment
Classifier: Intended Audience :: Developers
Classifier: License :: OSI Approved :: GNU General Public License v2 (GPLv2)
Classifier: Operating System :: OS Independent
Classifier: Programming Language :: Python
Classifier: Topic :: Internet :: WWW/HTTP :: Dynamic Content
Classifier: Topic :: Software Development :: Libraries :: Python Modules
Classifier: Programming Language :: Python :: 2
Classifier: Programming Language :: Python :: 2.7
Classifier: Programming Language :: Python :: 3
Classifier: Programming Language :: Python :: 3.5
Classifier: Development Status :: 1 - Planning
Provides-Extra: sqlite
Provides-Extra: postgresql
Provides-Extra: all
Provides-Extra: docs
Provides-Extra: tests
Provides-Extra: ui
Provides-Extra: mysql
